{
    "swagger": "2.0",
    "info": {
        "contact": {}
    },
    "basePath": "/api/v1",
    "paths": {
        "/ping": {
            "get": {
                "description": "Doing ping",
                "consumes": [
                    "application/json"
                ],
                "produces": [
                    "application/json"
                ],
                "tags": [
                    "Ping"
                ],
                "summary": "Ping example",
                "responses": {
                    "200": {
                        "description": "OK",
                        "schema": {
                            "type": "string"
                        }
                    }
                }
            }
        },
        "/ping2": {
            "get": {
                "description": "Doing ping",
                "consumes": [
                    "application/json"
                ],
                "produces": [
                    "application/json"
                ],
                "tags": [
                    "Ping2"
                ],
                "summary": "Ping2 example",
                "responses": {
                    "200": {
                        "description": "OK",
                        "schema": {
                            "type": "string"
                        }
                    }
                }
            }
        }
    }
}